[
  {
      "image_url": "https://raw.githubusercontent.com/joaomni/cdn/main/prof1.png",
      "title": "Fabio Russo",
      "subtitle": "Cirurgião dentista"
  },
  {
    "image_url": "https://raw.githubusercontent.com/joaomni/cdn/main/prof2.png",
    "title": "Martina Gallo ",
    "subtitle": "Assistente"
},
{
  "image_url": "https://raw.githubusercontent.com/joaomni/cdn/main/prof3.png",
  "title": "Luca Ferrero",
  "subtitle": "Higienista dental"
},
{
  "image_url": "https://raw.githubusercontent.com/joaomni/cdn/main/prof4.png",
  "title": "Giulia Santi",
  "subtitle": "Técnica dentário"
}
]